primopt/__init__.py
primopt-1.6.dist-info/LICENSE
primopt-1.6.dist-info/METADATA
primopt-1.6.dist-info/WHEEL
primopt-1.6.dist-info/top_level.txt
primopt-1.6.dist-info/RECORD
