Metadata-Version: 2.1
Name: primopt
Version: 1.6
Summary: A tool to perform mathematical operations on prime numbers.
Home-page: UNKNOWN
Author: Sergio Romero
Author-email: sergiorosen97@gmail.com
License: GNU GPLv3
Keywords: py mathematical operations
Platform: UNKNOWN
Classifier: Development Status :: 3 - Alpha
Classifier: Intended Audience :: Developers
Classifier: Topic :: Utilities
Classifier: License :: OSI Approved :: MIT License
Classifier: Programming Language :: Python :: 3
Classifier: Operating System :: OS Independent
License-File: LICENSE
